commodityapi-1.0.0.dist-info/licenses/LICENSE
comodityapi/API.py
comodityapi/__init__.py
comodityapi/constants.py
comodityapi/utils.py
commodityapi-1.0.0.dist-info/METADATA
commodityapi-1.0.0.dist-info/WHEEL
commodityapi-1.0.0.dist-info/top_level.txt
commodityapi-1.0.0.dist-info/RECORD
