Metadata-Version: 2.4
Name: commodityapi
Version: 1.0.0
Summary: Python SDK for commodity price data via API Freaks
Author: Muhammad Moeer
Author-email: Muhammad Moeer <moeer3505@gmail.com>
License: MIT
Requires-Python: >=3.7
License-File: LICENSE
Requires-Dist: requests>=2.20.0
Dynamic: author
Dynamic: license-file
Dynamic: requires-python
